pynyaasi/__init__.py
pynyaasi/client/__init__.py
pynyaasi/client/client.py
pynyaasi/client/directory.py
pynyaasi/client/enum.py
pynyaasi/client/size.py
pynyaasi/config/__init__.py
pynyaasi/config/meta.py
pynyaasi/nyaasi/__init__.py
pynyaasi/nyaasi/client.py
pynyaasi/nyaasi/enum.py
pynyaasi/sukebei/__init__.py
pynyaasi/sukebei/client.py
pynyaasi/sukebei/enum.py
pynyaasi/utils/__init__.py
pynyaasi/utils/enum.py
pynyaasi/utils/session.py
pynyaasi/utils/time.py
pynyaasi-0.1.0.dist-info/LICENSE
pynyaasi-0.1.0.dist-info/METADATA
pynyaasi-0.1.0.dist-info/WHEEL
pynyaasi-0.1.0.dist-info/top_level.txt
pynyaasi-0.1.0.dist-info/RECORD
